Workbook
Name Anos: Carteira!$F$21
Name Aporte: Carteira!$F$20
Name Proposta: Carteira!$F$16
Name Rendimento: Carteira!$F$15
Name Salario: Carteira!$F$14
Name Taxa: Carteira!$F$22

Sheet Carteira
B13: Configuração
B14: Salário | F14: 4600
B15: Rendimento da Carteira | F15: 0.006
B16: Investimento Sugerido (30%) | F16: =F14*30% -> 1380
B19: Investimento Mensal
B20: Quanto investir por mês? | F20: =Proposta -> 1380
B21: Por quantos anos? | F21: 5
B22: Taxa de rendimento mensal? | F22: 0.01079
B23: Patrimônio acumulado? | F23: =FV(Taxa,Anos*12,Aporte)*-1 -> 115612.14
B24: Dividendos mensais? | F24: =F23*Rendimento -> 693.67285
B27: Cenários | F27: Dividendos
B28: Quanto em 2 anos? | E28: =FV($F$22,2*12,$F$20)*-1 -> 37574.126 | F28: =E28*Rendimento -> 225.44475
B29: Quanto em 5 anos? | E29: =FV($F$22,5*12,$F$20)*-1 -> 115612.14 | F29: =E29*Rendimento -> 693.67285
B30: Quanto em 10 anos? | E30: =FV($F$22,10*12,$F$20)*-1 -> 335732.21 | F30: =E30*Rendimento -> 2014.3933
B31: Quanto em 20 anos? | E31: =FV($F$22,20*12,$F$20)*-1 -> 1552773.8 | F31: =E31*Rendimento -> 9316.6428
B32: Quanto em 30 anos? | E32: =FV($F$22,30*12,$F$20)*-1 -> 5964594.1 | F32: =E32*Rendimento -> 35787.565
B36: PERFIL | E36: Moderado
B37: VALOR A SER INVESTIDO por Mês | E37: =Aporte -> 1380
B39: Tipos de FII | E39: Percentual Sugerido | F39: Valores
B40: Papel | E40: =VLOOKUP($E$36&" - "&B40,Perfis!A4:D25,4,FALSE) -> 0.3 | F40: =E40*$E$37 -> 414
B41: Tijolo | E41: =VLOOKUP($E$36&" - "&B41,Perfis!A5:D26,4,FALSE) -> 0.35 | F41: =E41*$E$37 -> 483
B42: Híbrido | E42: =VLOOKUP($E$36&" - "&B42,Perfis!A6:D27,4,FALSE) -> 0.1 | F42: =E42*$E$37 -> 138
B43: FOFs | E43: =VLOOKUP($E$36&" - "&B43,Perfis!A7:D28,4,FALSE) -> 0.05 | F43: =E43*$E$37 -> 69
B44: Desenvolvimento | E44: =VLOOKUP($E$36&" - "&B44,Perfis!A8:D29,4,FALSE) -> 0.1 | F44: =E44*$E$37 -> 138
B45: Hotelarias | E45: =VLOOKUP($E$36&" - "&B45,Perfis!A9:D30,4,FALSE) -> 0.1 | F45: =E45*$E$37 -> 138
F46: =SUM(F40:F45) -> 1380

Sheet Perfis
A2: Proc Key (Chave Composta)
A4: =B4&" - "&C4 -> Conservador - Papel | B4: Conservador | C4: Papel | D4: 0.3
A5: =B5&" - "&C5 -> Conservador - Tijolo | B5: Conservador | C5: Tijolo | D5: 0.5
A6: =B6&" - "&C6 -> Conservador - Híbrido | B6: Conservador | C6: Híbrido | D6: 0.1
A7: =B7&" - "&C7 -> Conservador - FOFs | B7: Conservador | C7: FOFs | D7: 0.1
A8: =B8&" - "&C8 -> Conservador - Desenvolvimento | B8: Conservador | C8: Desenvolvimento | D8: 0
A9: =B9&" - "&C9 -> Conservador - Hotelarias | B9: Conservador | C9: Hotelarias | D9: 0
A12: =B12&" - "&C12 -> Moderado - Papel | B12: Moderado | C12: Papel | D12: 0.3
A13: =B13&" - "&C13 -> Moderado - Tijolo | B13: Moderado | C13: Tijolo | D13: 0.35
A14: =B14&" - "&C14 -> Moderado - Híbrido | B14: Moderado | C14: Híbrido | D14: 0.1
A15: =B15&" - "&C15 -> Moderado - FOFs | B15: Moderado | C15: FOFs | D15: 0.05
A16: =B16&" - "&C16 -> Moderado - Desenvolvimento | B16: Moderado | C16: Desenvolvimento | D16: 0.1
A17: =B17&" - "&C17 -> Moderado - Hotelarias | B17: Moderado | C17: Hotelarias | D17: 0.1
... A25: =B25&" - "&C25 -> Agressivo - Hotelarias | B25: Agressivo | C25: Hotelarias | D25: 0.1
